{
  "id": "sdk/v3/guides/advanced/introduction",
  "title": "introduction",
  "description": "For some more advanced use cases, it is necessary to use multiple tools in the SwapX toolchain.",
  "source": "@site/docs/sdk/v3/guides/advanced/01-introduction.md",
  "sourceDirName": "sdk/v3/guides/advanced",
  "slug": "/sdk/v3/guides/advanced/introduction",
  "permalink": "/sdk/v3/guides/advanced/introduction",
  "draft": false,
  "unlisted": false,
  "editUrl": "https://github.com/hi-swapx/docs/docs/sdk/v3/guides/advanced/01-introduction.md",
  "tags": [],
  "version": "current",
  "sidebarPosition": 1,
  "frontMatter": {
    "sidebar_label": "介绍",
    "sidebar_position": 1
  },
  "sidebar": "tutorialSidebar",
  "previous": {
    "title": "⚡ 先进的",
    "permalink": "/category/-先进的"
  },
  "next": {
    "title": "池数据",
    "permalink": "/sdk/v3/guides/advanced/pool-data"
  }
}